familyanalyzer/__init__.py
familyanalyzer/familyanalyzer.py
familyanalyzer/genetree.py
familyanalyzer/newick.py
familyanalyzer/orthoxmlquery.py
familyanalyzer/taxonomy.py
familyanalyzer/tools.py
familyanalyzer-0.7.3.data/scripts/familyanalyzer
familyanalyzer-0.7.3.dist-info/METADATA
familyanalyzer-0.7.3.dist-info/WHEEL
familyanalyzer-0.7.3.dist-info/top_level.txt
familyanalyzer-0.7.3.dist-info/RECORD
