Metadata-Version: 2.1
Name: familyanalyzer
Version: 0.7.3
Summary: A tool to analyse gene family evolution from orthoxml
Home-page: UNKNOWN
Author: Adrian Altenhoff
Author-email: adrian.altenhoff@inf.ethz.ch
License: MIT
Platform: UNKNOWN
Classifier: Development Status :: 3 - Alpha
Classifier: Intended Audience :: Developers
Classifier: Intended Audience :: Science/Research
Classifier: Topic :: Scientific/Engineering :: Bio-Informatics
Classifier: License :: OSI Approved :: MIT License
Classifier: Programming Language :: Python :: 2
Classifier: Programming Language :: Python :: 2.7
Classifier: Programming Language :: Python :: 3
Classifier: Programming Language :: Python :: 3.5
Classifier: Programming Language :: Python :: 3.6
Classifier: Programming Language :: Python :: 3.7
Classifier: Programming Language :: Python :: 3.8
Requires-Dist: lxml
Requires-Dist: progressbar-latest
Requires-Dist: future
